{"name":"Image Processor","tagline":"It is a simple rails application for processing image collections.","body":"# Image Processor\r\n\r\nIt is a simple rails application for processing image collections.\r\n\r\n## Features\r\n\r\n* authorization, managing users\r\n* creating hierarchy of nodes (like directories) with names, descriptions, statuses\r\n* uploading images\r\n* ordering images\r\n* inserting, duplicating\r\n* rotating and cropping\r\n* canceling changes\r\n* nice interface for viewing and processing image collections\r\n\r\n## Dependencies\r\n\r\n* MySQL\r\n* ImageMagick\r\n\r\n## Quick Start\r\n\r\n* git clone https://github.com/speranskydanil/image-processor.git\r\n* cp config/database.example.yml config/database.yml; vim config/database.yml\r\n* bin/rebuild -e p\r\n* rails server\r\n\r\nDefault login and password (seeds.rb): admin@company.com adminpassword\r\n\r\n## Rebuilding\r\n\r\n    bin/rebuild -h\r\n\r\n    Usage: bin/rebuild [options]\r\n\r\n    -f, --flags F        Flags for the rebuild script (by default all of them)\r\n                         l - bundle exec rake log:clear\r\n                         a - bundle exec rake assets:clean\r\n                         i - [ -e public/system ] && rm -R public/system/*\r\n                         d - bundle exec rake db:drop\r\n                         c - bundle exec rake db:create\r\n                         m - bundle exec rake db:schema:load\r\n                         s - bundle exec rake db:seed\r\n                         p - RAILS_ENV=production bundle exec rake assets:precompile\r\n                         j - [ -e bin/delayed_job ] && RAILS_ENV=production bin/delayed_job restart\r\n                         Example: dcms\r\n\r\n    -e, --except E       Except flags for the rebuild script\r\n                         See documentation for --flags\r\n\r\n## Updating\r\n\r\n    bin/update -h\r\n\r\n    Usage: bin/update [options]\r\n\r\n    -f, --flags F        Flags for the update script (by default all of them)\r\n                         l - bundle exec rake log:clear\r\n                         a - bundle exec rake assets:clean\r\n                         g - git pull\r\n                         b - bundle install\r\n                         m - bundle exec rake db:migrate\r\n                         p - RAILS_ENV=production bundle exec rake assets:precompile\r\n                         j - [ -e bin/delayed_job ] && RAILS_ENV=production bin/delayed_job restart\r\n                         Example: gm\r\n\r\n    -e, --except E       Except flags for the update script\r\n                         See documentation for --flags\r\n\r\n## Add Test Data\r\n\r\n    rake atd[path] # where path -- path to a directory with images\r\n\r\n## Screenshots\r\n\r\n![screen](https://raw.github.com/speranskydanil/image-processor/master/screens/1.png)\r\n\r\n![screen](https://raw.github.com/speranskydanil/image-processor/master/screens/2.png)\r\n\r\n![screen](https://raw.github.com/speranskydanil/image-processor/master/screens/3.png)\r\n\r\n![screen](https://raw.github.com/speranskydanil/image-processor/master/screens/4.png)\r\n\r\n![screen](https://raw.github.com/speranskydanil/image-processor/master/screens/5.png)\r\n\r\n![screen](https://raw.github.com/speranskydanil/image-processor/master/screens/6.png)\r\n\r\n**Author (Speransky Danil):**\r\n[Personal Page](http://dsperansky.info) |\r\n[LinkedIn](http://ru.linkedin.com/in/speranskydanil/en) |\r\n[GitHub](https://github.com/speranskydanil?tab=repositories) |\r\n[StackOverflow](http://stackoverflow.com/users/1550807/speransky-danil)\r\n\r\n","google":"UA-48799405-1","note":"Don't delete this file! It's used internally to help with page regeneration."}